{
    "https://mxb-mods.com/tcs-session-supercross/": {
        "url": "https://mxb-mods.com/tcs-session-supercross/",
        "title": "N/A",
        "creator": "N/A",
        "downloads": {
            "by_type": {
                "other": []
            },
            "by_host": {}
        },
        "images": {
            "cover": "",
            "additional": []
        },
        "description": "N/A",
        "embedded_videos": []
    },
    "https://mxb-mods.com/smoksta-flowsdale-mx/": {
        "url": "https://mxb-mods.com/smoksta-flowsdale-mx/",
        "title": "N/A",
        "creator": "N/A",
        "downloads": {
            "by_type": {
                "other": []
            },
            "by_host": {}
        },
        "images": {
            "cover": "",
            "additional": []
        },
        "description": "N/A",
        "embedded_videos": []
    },
    "https://mxb-mods.com/steezy93-snow-hills-freeride/": {
        "url": "https://mxb-mods.com/steezy93-snow-hills-freeride/",
        "title": "N/A",
        "creator": "N/A",
        "downloads": {
            "by_type": {
                "other": []
            },
            "by_host": {}
        },
        "images": {
            "cover": "",
            "additional": []
        },
        "description": "N/A",
        "embedded_videos": []
    },
    "https://mxb-mods.com/30-starter-maps/": {
        "url": "https://mxb-mods.com/30-starter-maps/",
        "title": "N/A",
        "creator": "N/A",
        "downloads": {
            "by_type": {
                "other": []
            },
            "by_host": {}
        },
        "images": {
            "cover": "",
            "additional": []
        },
        "description": "N/A",
        "embedded_videos": []
    },
    "https://mxb-mods.com/reix-2021-resolute-enduro-indoor-extreme/": {
        "url": "https://mxb-mods.com/reix-2021-resolute-enduro-indoor-extreme/",
        "title": "N/A",
        "creator": "N/A",
        "downloads": {
            "by_type": {
                "other": []
            },
            "by_host": {}
        },
        "images": {
            "cover": "",
            "additional": []
        },
        "description": "N/A",
        "embedded_videos": []
    }
}